{"info": {"address": null, "city": "Chatham", "country": "USA", "gmaps_place_id": null, "gmaps_url": null, "home_championship": {"2017": "St. Louis", "2018": "Detroit"}, "key": "frc1095", "lat": null, "lng": null, "location_name": null, "motto": null, "name": "Mid-Atlantic Broadband Communities Corporation / First Piedmont Corp. / Danville-Pittsylvania County Chamber of Commerce / Mecklenberg Electric Co-operative / Chatham Rotary Club / New London Technology / Pittsylvania Co. Schools & CHATHAM HIGH", "nickname": "Metal Minds", "postal_code": null, "rookie_year": 2003, "state_prov": "Virginia", "team_number": 1095, "website": null}, "events": [{"address": "1200 W Broad St, Richmond, VA 23284, USA", "city": "Richmond", "country": "USA", "district": null, "division_keys": [], "end_date": "2003-03-08", "event_code": "va", "event_type": 0, "event_type_string": "Regional", "first_event_id": "1246", "gmaps_place_id": "ChIJbUWI1U4RsYkRye-cYqUnP1E", "gmaps_url": "https://maps.google.com/?cid=5854441631882473417", "key": "2003va", "lat": 37.5529242, "lng": -77.4529507, "location_name": "Stuart C. Siegel Center", "name": "NASA / VCU Regional", "parent_event_key": null, "playoff_type": null, "playoff_type_string": null, "postal_code": "23284", "short_name": "NASA / VCU", "start_date": "2003-03-06", "state_prov": "VA", "timezone": "America/New_York", "webcasts": [], "website": "http://www.virginiafirst.org/", "week": 0, "year": 2003}, {"address": "1415 E Main St, Richmond, VA 23219, USA", "city": "Richmond", "country": "USA", "district": null, "division_keys": [], "end_date": "2004-03-06", "event_code": "va", "event_type": 0, "event_type_string": "Regional", "first_event_id": "1270", "gmaps_place_id": "ChIJ7YfmHxkRsYkRA-OsrJDbi-k", "gmaps_url": "https://maps.google.com/?cid=16828785847018775299", "key": "2004va", "lat": 37.535018, "lng": -77.4313477, "location_name": "Devon USA Inc", "name": "NASA / VCU Regional", "parent_event_key": null, "playoff_type": null, "playoff_type_string": null, "postal_code": "23219", "short_name": "NASA / VCU", "start_date": "2004-03-04", "state_prov": "VA", "timezone": "America/New_York", "webcasts": [], "website": "http://www.virginiafirst.org/", "week": 0, "year": 2004}, {"address": "1200 W Broad St, Richmond, VA 23284, USA", "city": "Richmond", "country": "USA", "district": null, "division_keys": [], "end_date": "2005-03-05", "event_code": "va", "event_type": 0, "event_type_string": "Regional", "first_event_id": "1297", "gmaps_place_id": "ChIJbUWI1U4RsYkRye-cYqUnP1E", "gmaps_url": "https://maps.google.com/?cid=5854441631882473417", "key": "2005va", "lat": 37.5529242, "lng": -77.4529507, "location_name": "Stuart C. Siegel Center", "name": "NASA / VCU Regional", "parent_event_key": null, "playoff_type": null, "playoff_type_string": null, "postal_code": "23284", "short_name": "NASA / VCU", "start_date": "2005-03-03", "state_prov": "VA", "timezone": "America/New_York", "webcasts": [], "website": "http://robots.larc.nasa.gov/competition/", "week": 0, "year": 2005}, {"address": "8032 W Broad St, Richmond, VA 23294, USA", "city": "Richmond", "country": "USA", "district": null, "division_keys": [], "end_date": "2006-03-04", "event_code": "va", "event_type": 0, "event_type_string": "Regional", "first_event_id": "1329", "gmaps_place_id": "ChIJ1bn1dBEVsYkRykrgi2BRG8s", "gmaps_url": "https://maps.google.com/?cid=14635380889176001226", "key": "2006va", "lat": 37.6272068, "lng": -77.5304641, "location_name": "HobbyTown USA", "name": "NASA / VCU Regional", "parent_event_key": null, "playoff_type": null, "playoff_type_string": null, "postal_code": "23294", "short_name": "VCU", "start_date": "2006-03-02", "state_prov": "VA", "timezone": "America/New_York", "webcasts": [], "website": "http://robots.larc.nasa.gov/competition/", "week": 0, "year": 2006}, {"address": "28 Westhampton Way, Richmond, VA 23173, USA", "city": "Richmond", "country": "USA", "district": null, "division_keys": [], "end_date": "2007-03-03", "event_code": "va", "event_type": 0, "event_type_string": "Regional", "first_event_id": "1414", "gmaps_place_id": "ChIJtXlSJ6IUsYkR_91m1Y4xCTE", "gmaps_url": "https://maps.google.com/?cid=3533409872184270335", "key": "2007va", "lat": 37.5739607, "lng": -77.53961369999999, "location_name": "University Of Richmond", "name": "NASA / VCU Regional", "parent_event_key": null, "playoff_type": null, "playoff_type_string": null, "postal_code": "23173", "short_name": "VCU", "start_date": "2007-03-01", "state_prov": "VA", "timezone": "America/New_York", "webcasts": [], "website": "http://www.virginiafirst.org", "week": 0, "year": 2007}, {"address": "Richmond, VA, USA", "city": "Richmond", "country": "USA", "district": null, "division_keys": [], "end_date": "2008-03-08", "event_code": "va", "event_type": 0, "event_type_string": "Regional", "first_event_id": null, "gmaps_place_id": "ChIJ7cmZVwkRsYkRxTxC4m0-2L8", "gmaps_url": "https://maps.google.com/?q=Richmond,+VA,+USA&ftid=0x89b111095799c9ed:0xbfd83e6de2423cc5", "key": "2008va", "lat": 37.5407246, "lng": -77.4360481, "location_name": null, "name": "NASA / VCU Regional", "parent_event_key": null, "playoff_type": null, "playoff_type_string": null, "postal_code": null, "short_name": "VCU", "start_date": "2008-03-06", "state_prov": "VA", "timezone": "America/New_York", "webcasts": [], "website": "http://www.virginiafirst.org/", "week": 1, "year": 2008}, {"address": "1200 W Broad St, Richmond, VA 23284, USA", "city": "Richmond", "country": "USA", "district": null, "division_keys": [], "end_date": "2009-03-21", "event_code": "va", "event_type": 0, "event_type_string": "Regional", "first_event_id": "2353", "gmaps_place_id": "ChIJbUWI1U4RsYkRye-cYqUnP1E", "gmaps_url": "https://maps.google.com/?cid=5854441631882473417", "key": "2009va", "lat": 37.5529242, "lng": -77.4529507, "location_name": "Stuart C. Siegel Center", "name": "NASA VCU Regional", "parent_event_key": null, "playoff_type": null, "playoff_type_string": null, "postal_code": "23284", "short_name": "NASA VCU", "start_date": "2009-03-19", "state_prov": "VA", "timezone": "America/New_York", "webcasts": [], "website": "http://www.virginiafirst.org", "week": 3, "year": 2009}, {"address": "1200 W Broad St, Richmond, VA 23284, USA", "city": "Richmond", "country": "USA", "district": null, "division_keys": [], "end_date": "2010-03-20", "event_code": "va", "event_type": 0, "event_type_string": "Regional", "first_event_id": "3739", "gmaps_place_id": "ChIJbUWI1U4RsYkRye-cYqUnP1E", "gmaps_url": "https://maps.google.com/?cid=5854441631882473417", "key": "2010va", "lat": 37.5529242, "lng": -77.4529507, "location_name": "Stuart C. Siegel Center", "name": "Virginia Regional", "parent_event_key": null, "playoff_type": null, "playoff_type_string": null, "postal_code": "23284", "short_name": "Virginia", "start_date": "2010-03-18", "state_prov": "VA", "timezone": "America/New_York", "webcasts": [], "website": "http://www.virginiafirst.org", "week": 2, "year": 2010}, {"address": "1200 W Broad St, Richmond, VA 23284, USA", "city": "Richmond", "country": "USA", "district": null, "division_keys": [], "end_date": "2011-04-09", "event_code": "va", "event_type": 0, "event_type_string": "Regional", "first_event_id": "5521", "gmaps_place_id": "ChIJbUWI1U4RsYkRye-cYqUnP1E", "gmaps_url": "https://maps.google.com/?cid=5854441631882473417", "key": "2011va", "lat": 37.5529242, "lng": -77.4529507, "location_name": "Stuart C. Siegel Center", "name": "Virginia Regional", "parent_event_key": null, "playoff_type": null, "playoff_type_string": null, "postal_code": "23284", "short_name": "Virginia", "start_date": "2011-04-07", "state_prov": "VA", "timezone": "America/New_York", "webcasts": [], "website": "http://www.virginiafirst.org", "week": 5, "year": 2011}, {"address": "1200 W Broad St, Richmond, VA 23284, USA", "city": "Richmond", "country": "USA", "district": null, "division_keys": [], "end_date": "2012-03-17", "event_code": "va", "event_type": 0, "event_type_string": "Regional", "first_event_id": "7587", "gmaps_place_id": "ChIJbUWI1U4RsYkRye-cYqUnP1E", "gmaps_url": "https://maps.google.com/?cid=5854441631882473417", "key": "2012va", "lat": 37.5529242, "lng": -77.4529507, "location_name": "Stuart C. Siegel Center", "name": "Virginia Regional", "parent_event_key": null, "playoff_type": null, "playoff_type_string": null, "postal_code": "23284", "short_name": "Virginia", "start_date": "2012-03-15", "state_prov": "VA", "timezone": "America/New_York", "webcasts": [], "website": "http://www.virginiafirst.org", "week": 2, "year": 2012}, {"address": "1200 W Broad St, Richmond, VA 23284, USA", "city": "Richmond", "country": "USA", "district": null, "division_keys": [], "end_date": "2013-03-16", "event_code": "vari", "event_type": 0, "event_type_string": "Regional", "first_event_id": "8945", "gmaps_place_id": "ChIJbUWI1U4RsYkRye-cYqUnP1E", "gmaps_url": "https://maps.google.com/?cid=5854441631882473417", "key": "2013vari", "lat": 37.5529242, "lng": -77.4529507, "location_name": "Stuart C. Siegel Center", "name": "Virginia Regional", "parent_event_key": null, "playoff_type": null, "playoff_type_string": null, "postal_code": "23284", "short_name": "Virginia", "start_date": "2013-03-14", "state_prov": "VA", "timezone": "America/New_York", "webcasts": [{"channel": "sargasso-4.arc.nasa.gov/live/", "file": "va_stream", "type": "rtmp"}], "website": "http://www.virginiafirst.org", "week": 2, "year": 2013}, {"address": "1200 W Broad St, Richmond, VA 23284, USA", "city": "Richmond", "country": "USA", "district": null, "division_keys": [], "end_date": "2014-03-22", "event_code": "vari", "event_type": 0, "event_type_string": "Regional", "first_event_id": "10751", "gmaps_place_id": "ChIJbUWI1U4RsYkRye-cYqUnP1E", "gmaps_url": "https://maps.google.com/?cid=5854441631882473417", "key": "2014vari", "lat": 37.5529242, "lng": -77.4529507, "location_name": "Stuart C. Siegel Center", "name": "Virginia Regional", "parent_event_key": null, "playoff_type": null, "playoff_type_string": null, "postal_code": "23284", "short_name": "Virginia", "start_date": "2014-03-20", "state_prov": "VA", "timezone": "America/New_York", "webcasts": [{"channel": "sargasso-4.arc.nasa.gov/live/", "file": "virginia", "type": "rtmp"}], "website": "http://www.virginiafirst.org", "week": 3, "year": 2014}, {"address": "1200 W Broad St, Richmond, VA 23284, USA", "city": "Richmond", "country": "USA", "district": null, "division_keys": [], "end_date": "2015-03-21", "event_code": "vari", "event_type": 0, "event_type_string": "Regional", "first_event_id": "13305", "gmaps_place_id": "ChIJbUWI1U4RsYkRye-cYqUnP1E", "gmaps_url": "https://maps.google.com/?cid=5854441631882473417", "key": "2015vari", "lat": 37.5529242, "lng": -77.4529507, "location_name": "Stuart C. Siegel Center", "name": "Virginia Regional", "parent_event_key": null, "playoff_type": 3, "playoff_type_string": "Average Score (8 Alliances)", "postal_code": "23284", "short_name": "Virginia", "start_date": "2015-03-18", "state_prov": "VA", "timezone": "America/New_York", "webcasts": [{"channel": "sargasso-4.arc.nasa.gov/live/", "file": "virginia", "type": "rtmp"}], "website": "http://www.virginiafirst.org", "week": 3, "year": 2015}], "districs": [], "awards": [{"award_type": 20, "event_key": "2007va", "name": "Xerox Creativity Award", "recipient_list": [{"awardee": null, "team_key": "frc1095"}], "year": 2007}, {"award_type": 2, "event_key": "2009va", "name": "Regional Finalist", "recipient_list": [{"awardee": null, "team_key": "frc1095"}, {"awardee": null, "team_key": "frc1522"}, {"awardee": null, "team_key": "frc384"}], "year": 2009}]}