{"info": {"address": null, "city": "Goodrich", "country": "USA", "gmaps_place_id": null, "gmaps_url": null, "home_championship": {"2017": "St. Louis", "2018": "Detroit"}, "key": "frc494", "lat": null, "lng": null, "location_name": null, "motto": "There is no substitute for hard work.  Thomas Edison ", "name": "General Motors/People of the state of Michigan/Fiat Chrysler Automotive Foundation/Kettering University/Leoni/Patti Engineering/Mid-Michigan Robotics Alliance/Burkland/Mid-States Bolt and Screw & Goodrich High School", "nickname": "Martians", "postal_code": "48438", "rookie_year": 2001, "state_prov": "Michigan", "team_number": 494, "website": "http://www.494themartians.com/"}, "events": [{"address": "8250 Exchange Dr # 100, Orlando, FL 32809, USA", "city": "Orlando", "country": "USA", "district": null, "division_keys": [], "end_date": "2001-03-24", "event_code": "mi1", "event_type": 0, "event_type_string": "Regional", "first_event_id": "1215", "gmaps_place_id": "ChIJkSYbtc1954gReueQd78UUuc", "gmaps_url": "https://maps.google.com/?cid=16668407983428921210", "key": "2001mi1", "lat": 28.444323, "lng": -81.414287, "location_name": "USA Today", "name": "Great Lakes Regional", "parent_event_key": null, "playoff_type": null, "playoff_type_string": null, "postal_code": "32809", "short_name": "Great Lakes", "start_date": "2001-03-22", "state_prov": "FL", "timezone": "America/New_York", "webcasts": [], "website": null, "week": 3, "year": 2001}, {"address": "8250 Exchange Dr # 100, Orlando, FL 32809, USA", "city": "Orlando", "country": "USA", "district": null, "division_keys": [], "end_date": "2002-03-23", "event_code": "gl", "event_type": 0, "event_type_string": "Regional", "first_event_id": "1228", "gmaps_place_id": "ChIJkSYbtc1954gReueQd78UUuc", "gmaps_url": "https://maps.google.com/?cid=16668407983428921210", "key": "2002gl", "lat": 28.444323, "lng": -81.414287, "location_name": "USA Today", "name": "Great Lakes Regional", "parent_event_key": null, "playoff_type": null, "playoff_type_string": null, "postal_code": "32809", "short_name": "Great Lakes", "start_date": "2002-03-21", "state_prov": "FL", "timezone": "America/New_York", "webcasts": [], "website": null, "week": 2, "year": 2002}, {"address": "Houston, TX, USA", "city": "Houston", "country": "USA", "district": null, "division_keys": ["2003arc", "2003cur", "2003gal", "2003new"], "end_date": "2003-04-12", "event_code": "cmp", "event_type": 4, "event_type_string": "Championship Finals", "first_event_id": null, "gmaps_place_id": "ChIJAYWNSLS4QIYROwVl894CDco", "gmaps_url": "https://maps.google.com/?q=Houston,+TX,+USA&ftid=0x8640b8b4488d8501:0xca0d02def365053b", "key": "2003cmp", "lat": 29.7604267, "lng": -95.3698028, "location_name": null, "name": "Einstein Field", "parent_event_key": null, "playoff_type": 0, "playoff_type_string": "Elimination Bracket (8 Alliances)", "postal_code": null, "short_name": "Einstein", "start_date": "2003-04-12", "state_prov": "TX", "timezone": "America/Chicago", "webcasts": [], "website": "http://www.usfirst.org", "week": null, "year": 2003}, {"address": "Houston, TX, USA", "city": "Houston", "country": "USA", "district": null, "division_keys": [], "end_date": "2003-04-12", "event_code": "cur", "event_type": 3, "event_type_string": "Championship Division", "first_event_id": null, "gmaps_place_id": "ChIJAYWNSLS4QIYROwVl894CDco", "gmaps_url": "https://maps.google.com/?q=Houston,+TX,+USA&ftid=0x8640b8b4488d8501:0xca0d02def365053b", "key": "2003cur", "lat": 29.7604267, "lng": -95.3698028, "location_name": null, "name": "Curie Division", "parent_event_key": "2003cmp", "playoff_type": 0, "playoff_type_string": "Elimination Bracket (8 Alliances)", "postal_code": null, "short_name": "Curie", "start_date": "2003-04-10", "state_prov": "TX", "timezone": "America/Chicago", "webcasts": [], "website": "http://www.usfirst.org", "week": null, "year": 2003}, {"address": "6400 Sugarloaf Pkwy, Duluth, GA 30097, USA", "city": "Duluth", "country": "USA", "district": null, "division_keys": [], "end_date": "2003-03-29", "event_code": "ga", "event_type": 0, "event_type_string": "Regional", "first_event_id": "1249", "gmaps_place_id": "ChIJs-HAukm99YgRaDS_WTVkGLg", "gmaps_url": "https://maps.google.com/?cid=13265462882721543272", "key": "2003ga", "lat": 33.9916226, "lng": -84.09392489999999, "location_name": "Infinite Energy Center", "name": "Peachtree Regional", "parent_event_key": null, "playoff_type": null, "playoff_type_string": null, "postal_code": "30097", "short_name": "Peachtree", "start_date": "2003-03-27", "state_prov": "GA", "timezone": "America/New_York", "webcasts": [], "website": "http://www.peachtreeregional.org/", "week": 3, "year": 2003}, {"address": "900 Oakwood St, Ypsilanti, MI 48197, USA", "city": "Ypsilanti", "country": "USA", "district": null, "division_keys": [], "end_date": "2003-03-22", "event_code": "gl", "event_type": 0, "event_type_string": "Regional", "first_event_id": "1256", "gmaps_place_id": "ChIJ9TNoGyupPIgRvbyZPIqSCZU", "gmaps_url": "https://maps.google.com/?cid=10739275908861508797", "key": "2003gl", "lat": 42.251677, "lng": -83.627405, "location_name": "Eastern Michigan University", "name": "Great Lakes Regional", "parent_event_key": null, "playoff_type": null, "playoff_type_string": null, "postal_code": "48197", "short_name": "Great Lakes", "start_date": "2003-03-20", "state_prov": "MI", "timezone": "America/New_York", "webcasts": [], "website": "http://www.greatlakesregional.com/", "week": 2, "year": 2003}, {"address": "2000 Prospect Ave E, Cleveland, OH 44115, USA", "city": "Cleveland", "country": "USA", "district": null, "division_keys": [], "end_date": "2003-03-08", "event_code": "oh", "event_type": 0, "event_type_string": "Regional", "first_event_id": "1253", "gmaps_place_id": "ChIJMxTU82P6MIgR150J1Hs3ACo", "gmaps_url": "https://maps.google.com/?cid=3026479954570878423", "key": "2003oh", "lat": 41.499205, "lng": -81.676497, "location_name": "Wolstein Center", "name": "Buckeye Regional", "parent_event_key": null, "playoff_type": null, "playoff_type_string": null, "postal_code": "44115", "short_name": "Buckeye", "start_date": "2003-03-06", "state_prov": "OH", "timezone": "America/New_York", "webcasts": [], "website": "http://www.firstbuckeye.org/", "week": 0, "year": 2003}, {"address": "Atlanta, GA, USA", "city": "Atlanta", "country": "USA", "district": null, "division_keys": [], "end_date": "2004-04-17", "event_code": "arc", "event_type": 3, "event_type_string": "Championship Division", "first_event_id": null, "gmaps_place_id": "ChIJjQmTaV0E9YgRC2MLmS_e_mY", "gmaps_url": "https://maps.google.com/?q=Atlanta,+GA,+USA&ftid=0x88f5045d6993098d:0x66fede2f990b630b", "key": "2004arc", "lat": 33.7489954, "lng": -84.3879824, "location_name": null, "name": "Archimedes Division", "parent_event_key": "2004cmp", "playoff_type": 0, "playoff_type_string": "Elimination Bracket (8 Alliances)", "postal_code": null, "short_name": "Archimedes", "start_date": "2004-04-15", "state_prov": "GA", "timezone": "America/New_York", "webcasts": [], "website": "http://www.usfirst.org", "week": null, "year": 2004}, {"address": "Atlanta, GA, USA", "city": "Atlanta", "country": "USA", "district": null, "division_keys": ["2004arc", "2004cur", "2004gal", "2004new"], "end_date": "2004-04-17", "event_code": "cmp", "event_type": 4, "event_type_string": "Championship Finals", "first_event_id": null, "gmaps_place_id": "ChIJjQmTaV0E9YgRC2MLmS_e_mY", "gmaps_url": "https://maps.google.com/?q=Atlanta,+GA,+USA&ftid=0x88f5045d6993098d:0x66fede2f990b630b", "key": "2004cmp", "lat": 33.7489954, "lng": -84.3879824, "location_name": null, "name": "Einstein Field", "parent_event_key": null, "playoff_type": 0, "playoff_type_string": "Elimination Bracket (8 Alliances)", "postal_code": null, "short_name": "Einstein", "start_date": "2004-04-17", "state_prov": "GA", "timezone": "America/New_York", "webcasts": [], "website": "http://www.usfirst.org", "week": null, "year": 2004}, {"address": "3099 Breckinridge Blvd, Duluth, GA 30095, USA", "city": "Duluth", "country": "USA", "district": null, "division_keys": [], "end_date": "2004-03-20", "event_code": "ga", "event_type": 0, "event_type_string": "Regional", "first_event_id": "1273", "gmaps_place_id": "ChIJ3bOqtTqj9YgRDdPbSMjhnL8", "gmaps_url": "https://maps.google.com/?cid=13807158807943172877", "key": "2004ga", "lat": 33.95686099999999, "lng": -84.11300179999999, "location_name": "Slim Girl Shapewear", "name": "Peachtree Regional", "parent_event_key": null, "playoff_type": null, "playoff_type_string": null, "postal_code": "30095", "short_name": "Peachtree", "start_date": "2004-03-18", "state_prov": "GA", "timezone": "America/New_York", "webcasts": [], "website": "http://www.peachtreeregional.org/", "week": 2, "year": 2004}, {"address": "2064 Whittaker Rd, Ypsilanti, MI 48197, USA", "city": "Ypsilanti", "country": "USA", "district": null, "division_keys": [], "end_date": "2004-03-13", "event_code": "gl", "event_type": 0, "event_type_string": "Regional", "first_event_id": "1280", "gmaps_place_id": "ChIJs7Oq8dunPIgRLyFb-6uRYBE", "gmaps_url": "https://maps.google.com/?cid=1252160864251486511", "key": "2004gl", "lat": 42.211183, "lng": -83.619465, "location_name": "Dollar USA", "name": "Great Lakes Regional", "parent_event_key": null, "playoff_type": null, "playoff_type_string": null, "postal_code": "48197", "short_name": "Great Lakes", "start_date": "2004-03-11", "state_prov": "MI", "timezone": "America/New_York", "webcasts": [], "website": "http://www.greatlakesregional.com/", "week": 1, "year": 2004}, {"address": "11700 48th Ave, Allendale, MI 49401, USA", "city": "Allendale Charter Township", "country": "USA", "district": null, "division_keys": [], "end_date": "2004-04-03", "event_code": "mi", "event_type": 0, "event_type_string": "Regional", "first_event_id": "1279", "gmaps_place_id": "ChIJVS5sIfeiGYgR9M0fYYXZDLQ", "gmaps_url": "https://maps.google.com/?cid=12973983793430908404", "key": "2004mi", "lat": 42.981339, "lng": -85.9020819, "location_name": "Charityusa.com LLC", "name": "West Michigan Regional", "parent_event_key": null, "playoff_type": null, "playoff_type_string": null, "postal_code": "49401", "short_name": "West Michigan", "start_date": "2004-04-01", "state_prov": "MI", "timezone": "America/New_York", "webcasts": [], "website": "http://www.westmichiganregional.com/", "week": 4, "year": 2004}, {"address": "Atlanta, GA, USA", "city": "Atlanta", "country": "USA", "district": null, "division_keys": [], "end_date": "2005-04-23", "event_code": "arc", "event_type": 3, "event_type_string": "Championship Division", "first_event_id": null, "gmaps_place_id": "ChIJjQmTaV0E9YgRC2MLmS_e_mY", "gmaps_url": "https://maps.google.com/?q=Atlanta,+GA,+USA&ftid=0x88f5045d6993098d:0x66fede2f990b630b", "key": "2005arc", "lat": 33.7489954, "lng": -84.3879824, "location_name": null, "name": "Archimedes Division", "parent_event_key": "2005cmp", "playoff_type": 0, "playoff_type_string": "Elimination Bracket (8 Alliances)", "postal_code": null, "short_name": "Archimedes", "start_date": "2005-04-21", "state_prov": "GA", "timezone": "America/New_York", "webcasts": [], "website": "http://www.usfirst.org", "week": null, "year": 2005}, {"address": "42 W Warren Ave, Detroit, MI 48202, USA", "city": "Detroit", "country": "USA", "district": null, "division_keys": [], "end_date": "2005-03-19", "event_code": "dt", "event_type": 0, "event_type_string": "Regional", "first_event_id": "1315", "gmaps_place_id": "ChIJQ9hCnbzSJIgRTl7fSYmWiLY", "gmaps_url": "https://maps.google.com/?cid=13152928228129594958", "key": "2005dt", "lat": 42.3591388, "lng": -83.06654619999999, "location_name": "Wayne State University", "name": "Detroit Regional", "parent_event_key": null, "playoff_type": null, "playoff_type_string": null, "postal_code": "48202", "short_name": "Detroit", "start_date": "2005-03-17", "state_prov": "MI", "timezone": "America/New_York", "webcasts": [], "website": "http://www.firstinmichigan.org/", "week": 2, "year": 2005}, {"address": "1 Campus Dr, Allendale, MI 49401, USA", "city": "Allendale Charter Township", "country": "USA", "district": null, "division_keys": [], "end_date": "2005-04-02", "event_code": "mi", "event_type": 0, "event_type_string": "Regional", "first_event_id": "1306", "gmaps_place_id": "ChIJjzmdDB-jGYgR-jLs4LNnA-o", "gmaps_url": "https://maps.google.com/?cid=16862435452075651834", "key": "2005mi", "lat": 42.9639355, "lng": -85.8889465, "location_name": "Grand Valley State University", "name": "West Michigan Regional", "parent_event_key": null, "playoff_type": null, "playoff_type_string": null, "postal_code": "49401", "short_name": "West Michigan", "start_date": "2005-03-31", "state_prov": "MI", "timezone": "America/New_York", "webcasts": [], "website": "http://www.westmichiganregional.com/", "week": 4, "year": 2005}, {"address": "1 Lomb Memorial Dr, Rochester, NY 14623, USA", "city": "Rochester", "country": "USA", "district": null, "division_keys": [], "end_date": "2005-03-05", "event_code": "roc", "event_type": 0, "event_type_string": "Regional", "first_event_id": "1319", "gmaps_place_id": "ChIJVX4UOmBM0YkRAyzi1R6zfr4", "gmaps_url": "https://maps.google.com/?cid=13726605659290610691", "key": "2005roc", "lat": 43.0861017, "lng": -77.6705143, "location_name": "Rochester Institute of Technology", "name": "Finger Lakes Regional", "parent_event_key": null, "playoff_type": null, "playoff_type_string": null, "postal_code": "14623", "short_name": "Finger Lakes", "start_date": "2005-03-03", "state_prov": "NY", "timezone": "America/New_York", "webcasts": [], "website": "http://www.firstrochester.org", "week": 0, "year": 2005}, {"address": "Atlanta, GA, USA", "city": "Atlanta", "country": "USA", "district": null, "division_keys": ["2006arc", "2006cur", "2006gal", "2006new"], "end_date": "2006-04-14", "event_code": "cmp", "event_type": 4, "event_type_string": "Championship Finals", "first_event_id": null, "gmaps_place_id": "ChIJjQmTaV0E9YgRC2MLmS_e_mY", "gmaps_url": "https://maps.google.com/?q=Atlanta,+GA,+USA&ftid=0x88f5045d6993098d:0x66fede2f990b630b", "key": "2006cmp", "lat": 33.7489954, "lng": -84.3879824, "location_name": null, "name": "Einstein Field", "parent_event_key": null, "playoff_type": 0, "playoff_type_string": "Elimination Bracket (8 Alliances)", "postal_code": null, "short_name": "Einstein", "start_date": "2006-04-14", "state_prov": "GA", "timezone": "America/New_York", "webcasts": [], "website": "http://www.usfirst.org", "week": null, "year": 2006}, {"address": "Atlanta, GA, USA", "city": "Atlanta", "country": "USA", "district": null, "division_keys": [], "end_date": "2006-04-14", "event_code": "gal", "event_type": 3, "event_type_string": "Championship Division", "first_event_id": null, "gmaps_place_id": "ChIJjQmTaV0E9YgRC2MLmS_e_mY", "gmaps_url": "https://maps.google.com/?q=Atlanta,+GA,+USA&ftid=0x88f5045d6993098d:0x66fede2f990b630b", "key": "2006gal", "lat": 33.7489954, "lng": -84.3879824, "location_name": null, "name": "Galileo Division", "parent_event_key": "2006cmp", "playoff_type": 0, "playoff_type_string": "Elimination Bracket (8 Alliances)", "postal_code": null, "short_name": "Galileo", "start_date": "2006-04-12", "state_prov": "GA", "timezone": "America/New_York", "webcasts": [], "website": "http://www.usfirst.org", "week": null, "year": 2006}, {"address": "11700 48th Ave, Allendale, MI 49401, USA", "city": "Allendale Charter Township", "country": "USA", "district": null, "division_keys": [], "end_date": "2006-04-01", "event_code": "mi", "event_type": 0, "event_type_string": "Regional", "first_event_id": "1354", "gmaps_place_id": "ChIJVS5sIfeiGYgR9M0fYYXZDLQ", "gmaps_url": "https://maps.google.com/?cid=12973983793430908404", "key": "2006mi", "lat": 42.981339, "lng": -85.9020819, "location_name": "Charityusa.com LLC", "name": "West Michigan Regional", "parent_event_key": null, "playoff_type": null, "playoff_type_string": null, "postal_code": "49401", "short_name": "West Michigan", "start_date": "2006-03-30", "state_prov": "MI", "timezone": "America/New_York", "webcasts": [], "website": "http://www.westmichiganregional.com", "week": 4, "year": 2006}, {"address": "4638 Fulton Rd, Cleveland, OH 44144, USA", "city": "Cleveland", "country": "USA", "district": null, "division_keys": [], "end_date": "2006-03-11", "event_code": "oh", "event_type": 0, "event_type_string": "Regional", "first_event_id": "1347", "gmaps_place_id": "ChIJwbcFfq_vMIgRVfjM1nE7x8g", "gmaps_url": "https://maps.google.com/?cid=14467597688072108117", "key": "2006oh", "lat": 41.43017, "lng": -81.724046, "location_name": "TIREMAN USA Fast Pit-Stop Service", "name": "Buckeye Regional", "parent_event_key": null, "playoff_type": null, "playoff_type_string": null, "postal_code": "44144", "short_name": "Buckeye", "start_date": "2006-03-09", "state_prov": "OH", "timezone": "America/New_York", "webcasts": [], "website": "http://www.firstbuckeye.org/", "week": 1, "year": 2006}, {"address": "2755 S 108th St, West Allis, WI 53227, USA", "city": "West Allis", "country": "USA", "district": null, "division_keys": [], "end_date": "2006-03-25", "event_code": "wi", "event_type": 0, "event_type_string": "Regional", "first_event_id": "1362", "gmaps_place_id": "ChIJA2PhQIMPBYgRQtxBrIAXOxA", "gmaps_url": "https://maps.google.com/?cid=1169554369646025794", "key": "2006wi", "lat": 42.993993, "lng": -88.047665, "location_name": "USA Payday Loans", "name": "Wisconsin Regional", "parent_event_key": null, "playoff_type": null, "playoff_type_string": null, "postal_code": "53227", "short_name": "Wisconsin", "start_date": "2006-03-23", "state_prov": "WI", "timezone": "America/Chicago", "webcasts": [], "website": "http://www.msoe.edu/wisconsinfrcregional", "week": 3, "year": 2006}, {"address": "Atlanta, GA, USA", "city": "Atlanta", "country": "USA", "district": null, "division_keys": [], "end_date": "2007-04-14", "event_code": "arc", "event_type": 3, "event_type_string": "Championship Division", "first_event_id": null, "gmaps_place_id": "ChIJjQmTaV0E9YgRC2MLmS_e_mY", "gmaps_url": "https://maps.google.com/?q=Atlanta,+GA,+USA&ftid=0x88f5045d6993098d:0x66fede2f990b630b", "key": "2007arc", "lat": 33.7489954, "lng": -84.3879824, "location_name": null, "name": "Archimedes Division", "parent_event_key": "2007cmp", "playoff_type": 0, "playoff_type_string": "Elimination Bracket (8 Alliances)", "postal_code": null, "short_name": "Archimedes", "start_date": "2007-04-12", "state_prov": "GA", "timezone": "America/New_York", "webcasts": [], "website": "http://www.usfirst.org", "week": null, "year": 2007}, {"address": "2064 Whittaker Rd, Ypsilanti, MI 48197, USA", "city": "Ypsilanti", "country": "USA", "district": null, "division_keys": [], "end_date": "2007-03-10", "event_code": "gl", "event_type": 0, "event_type_string": "Regional", "first_event_id": "1420", "gmaps_place_id": "ChIJs7Oq8dunPIgRLyFb-6uRYBE", "gmaps_url": "https://maps.google.com/?cid=1252160864251486511", "key": "2007gl", "lat": 42.211183, "lng": -83.619465, "location_name": "Dollar USA", "name": "Great Lakes Regional", "parent_event_key": null, "playoff_type": null, "playoff_type_string": null, "postal_code": "48197", "short_name": "GLR", "start_date": "2007-03-08", "state_prov": "MI", "timezone": "America/New_York", "webcasts": [], "website": "http://www.greatlakesregional.com", "week": 1, "year": 2007}, {"address": "Indianapolis, IN, USA", "city": "Indianapolis", "country": "USA", "district": null, "division_keys": [], "end_date": "2007-07-21", "event_code": "iri", "event_type": 99, "event_type_string": "Offseason", "first_event_id": null, "gmaps_place_id": "ChIJA2p5p_9Qa4gRfOq5QPadjtY", "gmaps_url": "https://maps.google.com/?q=Indianapolis,+IN,+USA&ftid=0x886b50ffa7796a03:0xd68e9df640b9ea7c", "key": "2007iri", "lat": 39.768403, "lng": -86.158068, "location_name": null, "name": "Indiana Robotics Invitational", "parent_event_key": null, "playoff_type": null, "playoff_type_string": null, "postal_code": null, "short_name": "IRI", "start_date": "2007-07-20", "state_prov": "IN", "timezone": "America/New_York", "webcasts": [], "website": "http://www.cyberblue234.com/iri/", "week": null, "year": 2007}, {"address": "11700 48th Ave, Allendale, MI 49401, USA", "city": "Allendale Charter Township", "country": "USA", "district": null, "division_keys": [], "end_date": "2007-03-31", "event_code": "mi", "event_type": 0, "event_type_string": "Regional", "first_event_id": "1439", "gmaps_place_id": "ChIJVS5sIfeiGYgR9M0fYYXZDLQ", "gmaps_url": "https://maps.google.com/?cid=12973983793430908404", "key": "2007mi", "lat": 42.981339, "lng": -85.9020819, "location_name": "Charityusa.com LLC", "name": "West Michigan Regional", "parent_event_key": null, "playoff_type": null, "playoff_type_string": null, "postal_code": "49401", "short_name": "W Michigan", "start_date": "2007-03-29", "state_prov": "MI", "timezone": "America/New_York", "webcasts": [], "website": "http://www.westmichiganregional.com", "week": 4, "year": 2007}, {"address": "2400 Orange Ave, Cleveland, OH 44101, USA", "city": "Cleveland", "country": "USA", "district": null, "division_keys": [], "end_date": "2007-03-24", "event_code": "oh", "event_type": 0, "event_type_string": "Regional", "first_event_id": "1432", "gmaps_place_id": "ChIJbctOEI76MIgRT6BeT3wXhdg", "gmaps_url": "https://maps.google.com/?cid=15601902306769936463", "key": "2007oh", "lat": 41.48987770000001, "lng": -81.6721602, "location_name": "US Post Office", "name": "Buckeye Regional", "parent_event_key": null, "playoff_type": null, "playoff_type_string": null, "postal_code": "44101", "short_name": "Buckeye", "start_date": "2007-03-22", "state_prov": "OH", "timezone": "America/New_York", "webcasts": [], "website": "http://www.firstbuckeye.org/", "week": 3, "year": 2007}, {"address": "Atlanta, GA, USA", "city": "Atlanta", "country": "USA", "district": null, "division_keys": [], "end_date": "2008-04-19", "event_code": "gal", "event_type": 3, "event_type_string": "Championship Division", "first_event_id": null, "gmaps_place_id": "ChIJjQmTaV0E9YgRC2MLmS_e_mY", "gmaps_url": "https://maps.google.com/?q=Atlanta,+GA,+USA&ftid=0x88f5045d6993098d:0x66fede2f990b630b", "key": "2008gal", "lat": 33.7489954, "lng": -84.3879824, "location_name": null, "name": "Galileo Division", "parent_event_key": "2008cmp", "playoff_type": 0, "playoff_type_string": "Elimination Bracket (8 Alliances)", "postal_code": null, "short_name": "Galileo", "start_date": "2008-04-17", "state_prov": "GA", "timezone": "America/New_York", "webcasts": [], "website": "http://www.usfirst.org", "week": null, "year": 2008}, {"address": "Ypsilanti, MI, USA", "city": "Ypsilanti", "country": "USA", "district": null, "division_keys": [], "end_date": "2008-03-29", "event_code": "gl", "event_type": 0, "event_type_string": "Regional", "first_event_id": null, "gmaps_place_id": "ChIJrfq42W2oPIgRUTRKX0D3xvk", "gmaps_url": "https://maps.google.com/?q=Ypsilanti,+MI,+USA&ftid=0x883ca86dd9b8faad:0xf9c6f7405f4a3451", "key": "2008gl", "lat": 42.2411499, "lng": -83.61299389999999, "location_name": null, "name": "Great Lakes Regional", "parent_event_key": null, "playoff_type": null, "playoff_type_string": null, "postal_code": null, "short_name": "GLR", "start_date": "2008-03-27", "state_prov": "MI", "timezone": "America/New_York", "webcasts": [], "website": "http://www.greatlakesregional.com/", "week": 4, "year": 2008}, {"address": "Indianapolis, IN, USA", "city": "Indianapolis", "country": "USA", "district": null, "division_keys": [], "end_date": "2008-07-19", "event_code": "iri", "event_type": 99, "event_type_string": "Offseason", "first_event_id": null, "gmaps_place_id": "ChIJA2p5p_9Qa4gRfOq5QPadjtY", "gmaps_url": "https://maps.google.com/?q=Indianapolis,+IN,+USA&ftid=0x886b50ffa7796a03:0xd68e9df640b9ea7c", "key": "2008iri", "lat": 39.768403, "lng": -86.158068, "location_name": null, "name": "Indiana Robotics Invitational", "parent_event_key": null, "playoff_type": null, "playoff_type_string": null, "postal_code": null, "short_name": "IRI", "start_date": "2008-07-18", "state_prov": "IN", "timezone": "America/New_York", "webcasts": [], "website": "http://indianaroboticsinvitational.org/iri/", "week": null, "year": 2008}, {"address": "Flint, MI, USA", "city": "Flint", "country": "USA", "district": null, "division_keys": [], "end_date": "2008-09-20", "event_code": "kk", "event_type": 100, "event_type_string": "Preseason", "first_event_id": null, "gmaps_place_id": "ChIJF3OXpft4I4gRa2gzjgk6hcE", "gmaps_url": "https://maps.google.com/?q=Flint,+MI,+USA&ftid=0x882378fba5977317:0xc1853a098e33686b", "key": "2008kk", "lat": 43.0125274, "lng": -83.6874562, "location_name": null, "name": "Kettering Kickoff", "parent_event_key": null, "playoff_type": null, "playoff_type_string": null, "postal_code": null, "short_name": "Kettering", "start_date": "2008-09-20", "state_prov": "MI", "timezone": "America/New_York", "webcasts": [], "website": "http://www.kettering.edu/visitors/events/ketteringkickoff.jsp", "week": null, "year": 2008}, {"address": "Allendale, Allendale Charter Twp, MI, USA", "city": "Allendale Charter Township", "country": "USA", "district": null, "division_keys": [], "end_date": "2008-03-22", "event_code": "mi", "event_type": 0, "event_type_string": "Regional", "first_event_id": null, "gmaps_place_id": "ChIJbdXY6V-YGYgRKlJFq001Lr8", "gmaps_url": "https://maps.google.com/?q=Allendale,+Allendale+Charter+Twp,+MI,+USA&ftid=0x8819985fe9d8d56d:0xbf2e354dab45522a", "key": "2008mi", "lat": 42.97219339999999, "lng": -85.9540407, "location_name": null, "name": "West Michigan Regional", "parent_event_key": null, "playoff_type": null, "playoff_type_string": null, "postal_code": null, "short_name": "W Michigan", "start_date": "2008-03-20", "state_prov": "MI", "timezone": "America/New_York", "webcasts": [], "website": "http://www.westmichiganregional.com/", "week": 3, "year": 2008}, {"address": "St Charles, MO, USA", "city": "Saint Charles", "country": "USA", "district": null, "division_keys": [], "end_date": "2008-03-01", "event_code": "mo", "event_type": 0, "event_type_string": "Regional", "first_event_id": null, "gmaps_place_id": "ChIJ4yTMiAgv34cRqvWMEavwN8Q", "gmaps_url": "https://maps.google.com/?q=St+Charles,+MO,+USA&ftid=0x87df2f0888cc24e3:0xc437f0ab118cf5aa", "key": "2008mo", "lat": 38.7881062, "lng": -90.4974359, "location_name": null, "name": "St. Louis Regional", "parent_event_key": null, "playoff_type": null, "playoff_type_string": null, "postal_code": null, "short_name": "St Louis", "start_date": "2008-02-28", "state_prov": "MO", "timezone": "America/Chicago", "webcasts": [], "website": "http://www.stlouisfirst.org/", "week": 0, "year": 2008}, {"address": "1 Georgia Dome Dr, Atlanta, GA 30313, USA", "city": "Atlanta", "country": "USA", "district": null, "division_keys": [], "end_date": "2009-04-18", "event_code": "gal", "event_type": 3, "event_type_string": "Championship Division", "first_event_id": null, "gmaps_place_id": "ChIJo0JlC34D9YgRcOAdejCWeBU", "gmaps_url": "https://maps.google.com/?cid=1547151606953140336", "key": "2009gal", "lat": 33.7576897, "lng": -84.40082850000002, "location_name": "Georgia Dome", "name": "Galileo Division", "parent_event_key": "2009cmp", "playoff_type": 0, "playoff_type_string": "Elimination Bracket (8 Alliances)", "postal_code": "30313", "short_name": "Galileo", "start_date": "2009-04-16", "state_prov": "GA", "timezone": "America/New_York", "webcasts": [], "website": "http://www.usfirst.org", "week": null, "year": 2009}, {"address": "1700 University Ave, Flint, MI 48504, USA", "city": "Flint", "country": "USA", "district": {"abbreviation": "fim", "display_name": "Michigan", "key": "2009fim", "year": 2009}, "division_keys": [], "end_date": "2009-03-07", "event_code": "gg", "event_type": 1, "event_type_string": "District", "first_event_id": "2495", "gmaps_place_id": "ChIJLx7Nx2SCI4gRzW8R94I3pEw", "gmaps_url": "https://maps.google.com/?cid=5522600078693461965", "key": "2009gg", "lat": 43.0114011, "lng": -83.712981, "location_name": "Kettering University", "name": "Kettering University FIRST Robotics District Competition", "parent_event_key": null, "playoff_type": null, "playoff_type_string": null, "postal_code": "48504", "short_name": "Kettering University", "start_date": "2009-03-06", "state_prov": "MI", "timezone": "America/New_York", "webcasts": [], "website": "http://www.firstinmichigan.org", "week": 1, "year": 2009}, {"address": "900 Oakwood St, Ypsilanti, MI 48197, USA", "city": "Ypsilanti", "country": "USA", "district": {"abbreviation": "fim", "display_name": "Michigan", "key": "2009fim", "year": 2009}, "division_keys": [], "end_date": "2009-04-04", "event_code": "gl", "event_type": 2, "event_type_string": "District Championship", "first_event_id": "2371", "gmaps_place_id": "ChIJ9TNoGyupPIgRvbyZPIqSCZU", "gmaps_url": "https://maps.google.com/?cid=10739275908861508797", "key": "2009gl", "lat": 42.25068029999999, "lng": -83.624089, "location_name": "Eastern Michigan University", "name": "Michigan FIRST Robotics Competition State Championship", "parent_event_key": null, "playoff_type": null, "playoff_type_string": null, "postal_code": "48197", "short_name": "Michigan", "start_date": "2009-04-02", "state_prov": "MI", "timezone": "America/New_York", "webcasts": [], "website": "http://www.firstinmichigan.org/index.php?topic=state_championship\r", "week": 5, "year": 2009}, {"address": "333 E Michigan Ave, Lansing, MI 48933, USA", "city": "Lansing", "country": "USA", "district": {"abbreviation": "fim", "display_name": "Michigan", "key": "2009fim", "year": 2009}, "division_keys": [], "end_date": "2009-03-21", "event_code": "grl", "event_type": 1, "event_type_string": "District", "first_event_id": "2497", "gmaps_place_id": "ChIJ09apTd_BIogRy83gwCpmJfM", "gmaps_url": "https://maps.google.com/?cid=17520522259165400523", "key": "2009grl", "lat": 42.734263, "lng": -84.5477343, "location_name": "Lansing Center", "name": "Lansing FIRST Robotics District Competition", "parent_event_key": null, "playoff_type": null, "playoff_type_string": null, "postal_code": "48933", "short_name": "Lansing", "start_date": "2009-03-20", "state_prov": "MI", "timezone": "America/New_York", "webcasts": [], "website": "http://www.firstinmichigan.org", "week": 3, "year": 2009}, {"address": "42 W Warren Ave, Detroit, MI 48202, USA", "city": "Detroit", "country": "USA", "district": {"abbreviation": "fim", "display_name": "Michigan", "key": "2010fim", "year": 2010}, "division_keys": [], "end_date": "2010-03-20", "event_code": "dt", "event_type": 1, "event_type_string": "District", "first_event_id": "3767", "gmaps_place_id": "ChIJQ9hCnbzSJIgRTl7fSYmWiLY", "gmaps_url": "https://maps.google.com/?cid=13152928228129594958", "key": "2010dt", "lat": 42.3591388, "lng": -83.06654619999999, "location_name": "Wayne State University", "name": "Detroit FIRST Robotics District Competition", "parent_event_key": null, "playoff_type": null, "playoff_type_string": null, "postal_code": "48202", "short_name": "Detroit", "start_date": "2010-03-19", "state_prov": "MI", "timezone": "America/New_York", "webcasts": [], "website": "http://www.firstinmichigan.org", "week": 2, "year": 2010}, {"address": "1700 University Ave, Flint, MI 48504, USA", "city": "Flint", "country": "USA", "district": {"abbreviation": "fim", "display_name": "Michigan", "key": "2010fim", "year": 2010}, "division_keys": [], "end_date": "2010-03-06", "event_code": "gg", "event_type": 1, "event_type_string": "District", "first_event_id": "3829", "gmaps_place_id": "ChIJLx7Nx2SCI4gRzW8R94I3pEw", "gmaps_url": "https://maps.google.com/?cid=5522600078693461965", "key": "2010gg", "lat": 43.0114011, "lng": -83.712981, "location_name": "Kettering University", "name": "Kettering University FIRST Robotics District Competition", "parent_event_key": null, "playoff_type": null, "playoff_type_string": null, "postal_code": "48504", "short_name": "Kettering University", "start_date": "2010-03-05", "state_prov": "MI", "timezone": "America/New_York", "webcasts": [], "website": "http://www.firstinmichigan.org", "week": 0, "year": 2010}, {"address": "900 Oakwood St, Ypsilanti, MI 48197, USA", "city": "Ypsilanti", "country": "USA", "district": {"abbreviation": "fim", "display_name": "Michigan", "key": "2010fim", "year": 2010}, "division_keys": [], "end_date": "2010-04-03", "event_code": "gl", "event_type": 2, "event_type_string": "District Championship", "first_event_id": "3755", "gmaps_place_id": "ChIJ9TNoGyupPIgRvbyZPIqSCZU", "gmaps_url": "https://maps.google.com/?cid=10739275908861508797", "key": "2010gl", "lat": 42.25068029999999, "lng": -83.624089, "location_name": "Eastern Michigan University", "name": "Michigan FIRST Robotics Competition State Championship", "parent_event_key": null, "playoff_type": null, "playoff_type_string": null, "postal_code": "48197", "short_name": "Michigan", "start_date": "2010-04-01", "state_prov": "MI", "timezone": "America/New_York", "webcasts": [], "website": "http://www.firstinmichigan.org/index.php?topic=state_championship\r", "week": 4, "year": 2010}, {"address": "1700 University Ave, Flint, MI 48504, USA", "city": "Flint", "country": "USA", "district": {"abbreviation": "fim", "display_name": "Michigan", "key": "2011fim", "year": 2011}, "division_keys": [], "end_date": "2011-03-05", "event_code": "gg", "event_type": 1, "event_type_string": "District", "first_event_id": "5611", "gmaps_place_id": "ChIJLx7Nx2SCI4gRzW8R94I3pEw", "gmaps_url": "https://maps.google.com/?cid=5522600078693461965", "key": "2011gg", "lat": 43.0114011, "lng": -83.712981, "location_name": "Kettering University", "name": "Kettering University FIRST Robotics District Competition", "parent_event_key": null, "playoff_type": null, "playoff_type_string": null, "postal_code": "48504", "short_name": "Kettering University", "start_date": "2011-03-04", "state_prov": "MI", "timezone": "America/New_York", "webcasts": [], "website": "http://www.firstinmichigan.org", "week": 0, "year": 2011}, {"address": "900 Oakwood St, Ypsilanti, MI 48197, USA", "city": "Ypsilanti", "country": "USA", "district": {"abbreviation": "fim", "display_name": "Michigan", "key": "2011fim", "year": 2011}, "division_keys": [], "end_date": "2011-04-09", "event_code": "gl", "event_type": 2, "event_type_string": "District Championship", "first_event_id": "5537", "gmaps_place_id": "ChIJ9TNoGyupPIgRvbyZPIqSCZU", "gmaps_url": "https://maps.google.com/?cid=10739275908861508797", "key": "2011gl", "lat": 42.25068029999999, "lng": -83.624089, "location_name": "Eastern Michigan University", "name": "Michigan FIRST Robotics District Competition State Championship", "parent_event_key": null, "playoff_type": null, "playoff_type_string": null, "postal_code": "48197", "short_name": "Michigan", "start_date": "2011-04-07", "state_prov": "MI", "timezone": "America/New_York", "webcasts": [], "website": "http://www.firstinmichigan.org/index.php?topic=state_championship\r", "week": 5, "year": 2011}, {"address": "901 N Broadway, St. Louis, MO 63101, USA", "city": "St. Louis", "country": "USA", "district": null, "division_keys": [], "end_date": "2011-04-30", "event_code": "new", "event_type": 3, "event_type_string": "Championship Division", "first_event_id": null, "gmaps_place_id": "ChIJwcWeSx-z2IcR7shA7mBLmOA", "gmaps_url": "https://maps.google.com/?cid=16183768140642044142", "key": "2011new", "lat": 38.6328287, "lng": -90.1885095, "location_name": "The Dome at America's Center", "name": "Newton Division", "parent_event_key": "2011cmp", "playoff_type": 0, "playoff_type_string": "Elimination Bracket (8 Alliances)", "postal_code": "63101", "short_name": "Newton Division", "start_date": "2011-04-27", "state_prov": "MO", "timezone": "America/Chicago", "webcasts": [], "website": "http://www.usfirst.org", "week": null, "year": 2011}, {"address": "2552 N Maple Rd, Ann Arbor, MI 48103, USA", "city": "Ann Arbor", "country": "USA", "district": {"abbreviation": "fim", "display_name": "Michigan", "key": "2011fim", "year": 2011}, "division_keys": [], "end_date": "2011-03-26", "event_code": "wc", "event_type": 1, "event_type_string": "District", "first_event_id": "5613", "gmaps_place_id": "ChIJG9kWDh6yPIgRZqpLi0lz8yI", "gmaps_url": "https://maps.google.com/?cid=2518483376337037926", "key": "2011wc", "lat": 42.30497070000001, "lng": -83.7777716, "location_name": "Skyline High School", "name": "Ann Arbor FIRST Robotics District Competition", "parent_event_key": null, "playoff_type": null, "playoff_type_string": null, "postal_code": "48103", "short_name": "Ann Arbor", "start_date": "2011-03-25", "state_prov": "MI", "timezone": "America/New_York", "webcasts": [], "website": "http://www.firstinmichigan.org", "week": 3, "year": 2011}, {"address": "1700 University Ave, Flint, MI 48504, USA", "city": "Flint", "country": "USA", "district": {"abbreviation": "fim", "display_name": "Michigan", "key": "2012fim", "year": 2012}, "division_keys": [], "end_date": "2012-03-03", "event_code": "gg", "event_type": 1, "event_type_string": "District", "first_event_id": "7677", "gmaps_place_id": "ChIJLx7Nx2SCI4gRzW8R94I3pEw", "gmaps_url": "https://maps.google.com/?cid=5522600078693461965", "key": "2012gg", "lat": 43.0114011, "lng": -83.712981, "location_name": "Kettering University", "name": "Kettering University FIRST Robotics District Competition", "parent_event_key": null, "playoff_type": null, "playoff_type_string": null, "postal_code": "48504", "short_name": "Kettering University", "start_date": "2012-03-02", "state_prov": "MI", "timezone": "America/New_York", "webcasts": [], "website": "http://www.firstinmichigan.org", "week": 0, "year": 2012}, {"address": "900 Oakwood St, Ypsilanti, MI 48197, USA", "city": "Ypsilanti", "country": "USA", "district": {"abbreviation": "fim", "display_name": "Michigan", "key": "2012fim", "year": 2012}, "division_keys": [], "end_date": "2012-04-14", "event_code": "gl", "event_type": 2, "event_type_string": "District Championship", "first_event_id": "7603", "gmaps_place_id": "ChIJ9TNoGyupPIgRvbyZPIqSCZU", "gmaps_url": "https://maps.google.com/?cid=10739275908861508797", "key": "2012gl", "lat": 42.25068029999999, "lng": -83.624089, "location_name": "Eastern Michigan University", "name": "Michigan FRC State Championship", "parent_event_key": null, "playoff_type": null, "playoff_type_string": null, "postal_code": "48197", "short_name": "Michigan", "start_date": "2012-04-12", "state_prov": "MI", "timezone": "America/New_York", "webcasts": [], "website": "http://www.firstinmichigan.org/index.php?topic=state_championship\r", "week": 6, "year": 2012}, {"address": "1441 Eagle St, Niles, MI 49120, USA", "city": "Niles", "country": "USA", "district": {"abbreviation": "fim", "display_name": "Michigan", "key": "2012fim", "year": 2012}, "division_keys": [], "end_date": "2012-03-24", "event_code": "swm", "event_type": 1, "event_type_string": "District", "first_event_id": "7701", "gmaps_place_id": "ChIJY0DtwD7VFogRwv49fJ3dkcI", "gmaps_url": "https://maps.google.com/?cid=14020230783445106370", "key": "2012swm", "lat": 41.835772, "lng": -86.2391907, "location_name": "Niles High School", "name": "Niles FIRST Robotics District Competition", "parent_event_key": null, "playoff_type": null, "playoff_type_string": null, "postal_code": "49120", "short_name": "Niles", "start_date": "2012-03-23", "state_prov": "MI", "timezone": "America/New_York", "webcasts": [], "website": "http://www.firstinmichigan.org", "week": 3, "year": 2012}, {"address": "799 North Hewitt Road, Ypsilanti, MI 48197, USA", "city": "Ypsilanti", "country": "USA", "district": {"abbreviation": "fim", "display_name": "Michigan", "key": "2013fim", "year": 2013}, "division_keys": [], "end_date": "2013-04-13", "event_code": "micmp", "event_type": 2, "event_type_string": "District Championship", "first_event_id": "8961", "gmaps_place_id": "ChIJg0q5juSoPIgR__6SQcAOWzE", "gmaps_url": "https://maps.google.com/?cid=3556452549635800831", "key": "2013micmp", "lat": 42.2542182, "lng": -83.6473247, "location_name": "Eastern Michigan University Convocation Center", "name": "Michigan FRC State Championship", "parent_event_key": null, "playoff_type": null, "playoff_type_string": null, "postal_code": "48197", "short_name": "Michigan", "start_date": "2013-04-11", "state_prov": "MI", "timezone": "America/New_York", "webcasts": [{"channel": "6602291", "type": "ustream"}, {"channel": "539046", "type": "ustream"}, {"channel": "firstinmichigan", "type": "twitch"}], "website": "http://www.firstinmichigan.org", "week": 6, "year": 2013}, {"address": "Michigan, USA", "city": "Michigan", "country": "USA", "district": null, "division_keys": [], "end_date": "2013-09-21", "event_code": "mikk", "event_type": 99, "event_type_string": "Offseason", "first_event_id": "off-season-kettering-kickoff-competition-2013", "gmaps_place_id": "ChIJEQTKxz2qTE0Rs8liellI3Zc", "gmaps_url": "https://maps.google.com/?q=Michigan,+USA&ftid=0x4d4caa3dc7ca0411:0x97dd48597a62c9b3", "key": "2013mikk", "lat": 44.3148443, "lng": -85.60236429999999, "location_name": null, "name": "Kettering Kickoff", "parent_event_key": null, "playoff_type": null, "playoff_type_string": null, "postal_code": null, "short_name": null, "start_date": "2013-09-20", "state_prov": "MI", "timezone": "America/New_York", "webcasts": [], "website": null, "week": null, "year": 2013}, {"address": "1151 Scott Lake Rd, Waterford Twp, MI 48328, USA", "city": "Waterford Township", "country": "USA", "district": {"abbreviation": "fim", "display_name": "Michigan", "key": "2013fim", "year": 2013}, "division_keys": [], "end_date": "2013-03-09", "event_code": "miwfd", "event_type": 1, "event_type_string": "District", "first_event_id": "9061", "gmaps_place_id": "ChIJ2-4mm3G9JIgRDosg0swmCIs", "gmaps_url": "https://maps.google.com/?cid=10018300032226200334", "key": "2013miwfd", "lat": 42.6564663, "lng": -83.3490497, "location_name": "Waterford Mott High School", "name": "Waterford FIRST Robotics District Competition", "parent_event_key": null, "playoff_type": null, "playoff_type_string": null, "postal_code": "48328", "short_name": "Waterford", "start_date": "2013-03-08", "state_prov": "MI", "timezone": "America/New_York", "webcasts": [{"channel": "6602266", "type": "ustream"}], "website": "http://www.firstinmichigan.org", "week": 1, "year": 2013}, {"address": "222 Fairbanks Ave, Holland, MI 49423, USA", "city": "Holland", "country": "USA", "district": {"abbreviation": "fim", "display_name": "Michigan", "key": "2013fim", "year": 2013}, "division_keys": [], "end_date": "2013-03-23", "event_code": "miwmi", "event_type": 1, "event_type_string": "District", "first_event_id": "9013", "gmaps_place_id": "ChIJoc_5aKjyGYgRUS6lqydwjWI", "gmaps_url": "https://maps.google.com/?cid=7101455503118904913", "key": "2013miwmi", "lat": 42.7887273, "lng": -86.09548240000001, "location_name": "DeVos Fieldhouse", "name": "West Michigan FIRST Robotics District Competition", "parent_event_key": null, "playoff_type": null, "playoff_type_string": null, "postal_code": "49423", "short_name": "West Michigan", "start_date": "2013-03-22", "state_prov": "MI", "timezone": "America/New_York", "webcasts": [{"channel": "6602252", "type": "ustream"}], "website": "http://www.firstinmichigan.org", "week": 3, "year": 2013}, {"address": "St. Louis, MO, USA", "city": "St. Louis", "country": "USA", "district": null, "division_keys": [], "end_date": "2014-04-26", "event_code": "gal", "event_type": 3, "event_type_string": "Championship Division", "first_event_id": null, "gmaps_place_id": "ChIJ-Y7t-qm02IcRW-C7IsrqOb4", "gmaps_url": "https://maps.google.com/?q=St.+Louis,+MO,+USA&ftid=0x87d8b4a9faed8ef9:0xbe39eaca22bbe05b", "key": "2014gal", "lat": 38.6270025, "lng": -90.19940419999999, "location_name": null, "name": "Galileo Division", "parent_event_key": "2014cmp", "playoff_type": 0, "playoff_type_string": "Elimination Bracket (8 Alliances)", "postal_code": null, "short_name": "Galileo", "start_date": "2014-04-24", "state_prov": "MO", "timezone": "America/Chicago", "webcasts": [{"channel": "<iframe src=\"http://diglumi.com/gameday/#3\" width=\"100%\" height=\"100%\" frameborder=\"no\" style=\"border-style: none;\"></iframe>", "type": "iframe"}], "website": "", "week": null, "year": 2014}, {"address": "7802 Hague Rd, Indianapolis, IN 46256, USA", "city": "Indianapolis", "country": "USA", "district": null, "division_keys": [], "end_date": "2014-07-19", "event_code": "iri", "event_type": 99, "event_type_string": "Offseason", "first_event_id": "off-season-indiana-robotics-invitational-2014", "gmaps_place_id": "ChIJt-fTNsJMa4gRk20afFmPaQU", "gmaps_url": "https://maps.google.com/?cid=390000457241226643", "key": "2014iri", "lat": 39.8961663, "lng": -86.0349536, "location_name": "Lawrence North High School", "name": "Indiana Robotics Invitational", "parent_event_key": null, "playoff_type": null, "playoff_type_string": null, "postal_code": "46256", "short_name": "IRI", "start_date": "2014-07-18", "state_prov": "IN", "timezone": "America/New_York", "webcasts": [{"channel": "18515481", "type": "ustream"}, {"channel": "18515505", "type": "ustream"}], "website": "http://www.indianaroboticsinvitational.org/", "week": null, "year": 2014}, {"address": "8285 Jackman Rd, Temperance, MI 48182, USA", "city": "Temperance", "country": "USA", "district": {"abbreviation": "fim", "display_name": "Michigan", "key": "2014fim", "year": 2014}, "division_keys": [], "end_date": "2014-04-05", "event_code": "mibed", "event_type": 1, "event_type_string": "District", "first_event_id": "10905", "gmaps_place_id": "ChIJq7p8_Nl_O4gRmGnvOahzIc0", "gmaps_url": "https://maps.google.com/?cid=14781222618370369944", "key": "2014mibed", "lat": 41.76615839999999, "lng": -83.58810419999999, "location_name": "Bedford High School", "name": "Bedford FIRST Robotics District Competition", "parent_event_key": null, "playoff_type": null, "playoff_type_string": null, "postal_code": "48182", "short_name": "Bedford", "start_date": "2014-04-04", "state_prov": "MI", "timezone": "America/New_York", "webcasts": [{"channel": "vdjL0x-FgAI", "type": "youtube"}, {"channel": "6sGgYLeuvHY", "type": "youtube"}], "website": "http://www.firstinmichigan.org", "week": 5, "year": 2014}, {"address": "26300 Arsenal St, Center Line, MI 48015, USA", "city": "Center Line", "country": "USA", "district": {"abbreviation": "fim", "display_name": "Michigan", "key": "2014fim", "year": 2014}, "division_keys": [], "end_date": "2014-03-01", "event_code": "micen", "event_type": 1, "event_type_string": "District", "first_event_id": "10841", "gmaps_place_id": "ChIJBxadQprQJIgRNZo0vGznxEA", "gmaps_url": "https://maps.google.com/?cid=4667109568062724661", "key": "2014micen", "lat": 42.4867326, "lng": -83.02047549999999, "location_name": "Center Line High School", "name": "Center Line FIRST Robotics District Competition", "parent_event_key": null, "playoff_type": null, "playoff_type_string": null, "postal_code": "48015", "short_name": "Center Line", "start_date": "2014-02-28", "state_prov": "MI", "timezone": "America/New_York", "webcasts": [{"channel": "17345485", "type": "ustream"}], "website": "http://www.firstinmichigan.org", "week": 0, "year": 2014}, {"address": "900 Oakwood St, Ypsilanti, MI 48197, USA", "city": "Ypsilanti", "country": "USA", "district": {"abbreviation": "fim", "display_name": "Michigan", "key": "2014fim", "year": 2014}, "division_keys": [], "end_date": "2014-04-12", "event_code": "micmp", "event_type": 2, "event_type_string": "District Championship", "first_event_id": "10767", "gmaps_place_id": "ChIJ9TNoGyupPIgRvbyZPIqSCZU", "gmaps_url": "https://maps.google.com/?cid=10739275908861508797", "key": "2014micmp", "lat": 42.25068029999999, "lng": -83.624089, "location_name": "Eastern Michigan University", "name": "Michigan FRC State Championship", "parent_event_key": null, "playoff_type": null, "playoff_type_string": null, "postal_code": "48197", "short_name": "Michigan", "start_date": "2014-04-10", "state_prov": "MI", "timezone": "America/New_York", "webcasts": [{"channel": "17345485", "type": "ustream"}, {"channel": "1408609", "file": "2886512", "type": "livestream"}], "website": "http://www.firstinmichigan.org", "week": 6, "year": 2014}, {"address": "1 Campus Dr, Allendale, MI 49401, USA", "city": "Allendale Charter Township", "country": "USA", "district": {"abbreviation": "fim", "display_name": "Michigan", "key": "2014fim", "year": 2014}, "division_keys": [], "end_date": "2014-03-22", "event_code": "miwmi", "event_type": 1, "event_type_string": "District", "first_event_id": "10819", "gmaps_place_id": "ChIJjzmdDB-jGYgR-jLs4LNnA-o", "gmaps_url": "https://maps.google.com/?cid=16862435452075651834", "key": "2014miwmi", "lat": 42.9639355, "lng": -85.8889465, "location_name": "Grand Valley State University", "name": "West Michigan FIRST Robotics District Competition", "parent_event_key": null, "playoff_type": null, "playoff_type_string": null, "postal_code": "49401", "short_name": "West Michigan", "start_date": "2014-03-21", "state_prov": "MI", "timezone": "America/New_York", "webcasts": [{"channel": "17345485", "type": "ustream"}], "website": "http://www.firstinmichigan.org", "week": 3, "year": 2014}, {"address": "St. Louis, MO, USA", "city": "St. Louis", "country": "USA", "district": null, "division_keys": [], "end_date": "2015-04-25", "event_code": "gal", "event_type": 3, "event_type_string": "Championship Division", "first_event_id": null, "gmaps_place_id": "ChIJ-Y7t-qm02IcRW-C7IsrqOb4", "gmaps_url": "https://maps.google.com/?q=St.+Louis,+MO,+USA&ftid=0x87d8b4a9faed8ef9:0xbe39eaca22bbe05b", "key": "2015gal", "lat": 38.6270025, "lng": -90.19940419999999, "location_name": null, "name": "Galileo Division", "parent_event_key": "2015cmp", "playoff_type": 3, "playoff_type_string": "Average Score (8 Alliances)", "postal_code": null, "short_name": "Galileo", "start_date": "2015-04-22", "state_prov": "MO", "timezone": "America/Chicago", "webcasts": [{"channel": "http://ksc-event5.infozen.cshls.lldns.net/infozen/ksc-event5/ksc-event5.m3u8", "type": "html5"}], "website": "", "week": null, "year": 2015}, {"address": "901 Herr Rd, Monroe, MI 48161, USA", "city": "Monroe", "country": "USA", "district": null, "division_keys": [], "end_date": "2015-06-20", "event_code": "marc", "event_type": 99, "event_type_string": "Offseason", "first_event_id": null, "gmaps_place_id": "ChIJT3WU9m1lO4gR0AFkBHnf3Dc", "gmaps_url": "https://maps.google.com/?cid=4025337877820080592", "key": "2015marc", "lat": 41.918565, "lng": -83.437085, "location_name": "Monroe High School", "name": "Michigan Advanced Robotics Competition", "parent_event_key": null, "playoff_type": 3, "playoff_type_string": "Average Score (8 Alliances)", "postal_code": "48161", "short_name": null, "start_date": "2015-06-19", "state_prov": "MI", "timezone": "America/New_York", "webcasts": [], "website": null, "week": null, "year": 2015}, {"address": "2500 Turner Ave NW, Grand Rapids, MI 49544, USA", "city": "Grand Rapids", "country": "USA", "district": {"abbreviation": "fim", "display_name": "Michigan", "key": "2015fim", "year": 2015}, "division_keys": [], "end_date": "2015-04-11", "event_code": "micmp", "event_type": 2, "event_type_string": "District Championship", "first_event_id": "13321", "gmaps_place_id": "ChIJ1dOHdQOsGYgRnT51UD1muYw", "gmaps_url": "https://maps.google.com/?cid=10140248449530281629", "key": "2015micmp", "lat": 43.0096402, "lng": -85.6807832, "location_name": "DeltaPlex Arena", "name": "FIRST in Michigan District Championship", "parent_event_key": null, "playoff_type": 3, "playoff_type_string": "Average Score (8 Alliances)", "postal_code": "49544", "short_name": "FIRST in Michigan", "start_date": "2015-04-08", "state_prov": "MI", "timezone": "America/New_York", "webcasts": [{"channel": "firstinmichigan", "type": "twitch"}, {"channel": "firstinmichigan2", "type": "twitch"}, {"channel": "firstinmichigan3", "type": "twitch"}], "website": "http://www.firstinmichigan.org", "week": 6, "year": 2015}, {"address": "400 Wright Rd, Howell, MI 48843, USA", "city": "Howell", "country": "USA", "district": {"abbreviation": "fim", "display_name": "Michigan", "key": "2015fim", "year": 2015}, "division_keys": [], "end_date": "2015-02-28", "event_code": "mihow", "event_type": 1, "event_type_string": "District", "first_event_id": "13417", "gmaps_place_id": "ChIJN2g4qPRHI4gReOm1Nd0HQYI", "gmaps_url": "https://maps.google.com/?cid=9385791745087105400", "key": "2015mihow", "lat": 42.565648, "lng": -83.9274081, "location_name": "Parker Middle School", "name": "FIM District - Howell Event", "parent_event_key": null, "playoff_type": 3, "playoff_type_string": "Average Score (8 Alliances)", "postal_code": "48843", "short_name": "Howell", "start_date": "2015-02-26", "state_prov": "MI", "timezone": "America/New_York", "webcasts": [{"channel": "firstinmichigan", "type": "twitch"}], "website": "http://www.firstinmichigan.org", "week": 0, "year": 2015}, {"address": "2521 Stadium Dr, St Joseph, MI 49085, USA", "city": "Saint Joseph", "country": "USA", "district": {"abbreviation": "fim", "display_name": "Michigan", "key": "2015fim", "year": 2015}, "division_keys": [], "end_date": "2015-03-21", "event_code": "misjo", "event_type": 1, "event_type_string": "District", "first_event_id": "13413", "gmaps_place_id": "ChIJCVkXmw7EEIgRxoMdcmN8zUo", "gmaps_url": "https://maps.google.com/?cid=5390101095590495174", "key": "2015misjo", "lat": 42.089441, "lng": -86.492801, "location_name": "St. Joseph High School", "name": "FIM District - St. Joseph Event", "parent_event_key": null, "playoff_type": 3, "playoff_type_string": "Average Score (8 Alliances)", "postal_code": "49085", "short_name": "St. Joseph", "start_date": "2015-03-19", "state_prov": "MI", "timezone": "America/New_York", "webcasts": [{"channel": "firstinmichigan3", "type": "twitch"}], "website": "http://www.firstinmichigan.org", "week": 3, "year": 2015}, {"address": "901 N Broadway, St. Louis, MO 63101, USA", "city": "St. Louis", "country": "USA", "district": null, "division_keys": [], "end_date": "2016-04-30", "event_code": "gal", "event_type": 3, "event_type_string": "Championship Division", "first_event_id": null, "gmaps_place_id": "ChIJwcWeSx-z2IcR7shA7mBLmOA", "gmaps_url": "https://maps.google.com/?cid=16183768140642044142", "key": "2016gal", "lat": 38.6328287, "lng": -90.1885095, "location_name": "The Dome at America's Center", "name": "Galileo Division", "parent_event_key": "2016cmp", "playoff_type": 0, "playoff_type_string": "Elimination Bracket (8 Alliances)", "postal_code": "63101", "short_name": "Galileo", "start_date": "2016-04-27", "state_prov": "MO", "timezone": "America/Chicago", "webcasts": [{"channel": "first_galileo", "type": "twitch"}], "website": null, "week": null, "year": 2016}, {"address": "Indianapolis, IN, USA", "city": "Indianapolis", "country": "USA", "district": null, "division_keys": [], "end_date": "2016-07-16", "event_code": "iri", "event_type": 99, "event_type_string": "Offseason", "first_event_id": null, "gmaps_place_id": "ChIJA2p5p_9Qa4gRfOq5QPadjtY", "gmaps_url": "https://maps.google.com/?q=Indianapolis,+IN,+USA&ftid=0x886b50ffa7796a03:0xd68e9df640b9ea7c", "key": "2016iri", "lat": 39.768403, "lng": -86.158068, "location_name": null, "name": "Indiana Robotics Invitational", "parent_event_key": null, "playoff_type": null, "playoff_type_string": null, "postal_code": null, "short_name": "IRI", "start_date": "2016-07-15", "state_prov": "IN", "timezone": "America/New_York", "webcasts": [{"channel": "17904105", "file": "5838331", "type": "livestream"}], "website": "http://indianaroboticsinvitational.org/", "week": null, "year": 2016}, {"address": null, "city": "Grand Rapids", "country": "USA", "district": {"abbreviation": "fim", "display_name": "Michigan", "key": "2016fim", "year": 2016}, "division_keys": [], "end_date": "2016-04-16", "event_code": "micmp", "event_type": 2, "event_type_string": "District Championship", "first_event_id": "17317", "gmaps_place_id": null, "gmaps_url": null, "key": "2016micmp", "lat": null, "lng": null, "location_name": null, "name": "Michigan State Championship", "parent_event_key": null, "playoff_type": null, "playoff_type_string": null, "postal_code": "48544", "short_name": "Michigan", "start_date": "2016-04-13", "state_prov": "MI", "timezone": "America/New_York", "webcasts": [{"channel": "<iframe src=\"http://iframe.dacast.com/b/66716/c/219332\" width=\"100%\" height=\"100%\" frameborder=\"0\" scrolling=\"no\" allowfullscreen webkitallowfullscreen mozallowfullscreen oallowfullscreen msallowfullscreen></iframe>", "type": "iframe"}], "website": "http://www.firstinmichigan.org", "week": 7, "year": 2016}, {"address": "400 Wright Rd, Howell, MI 48843, USA", "city": "Howell", "country": "USA", "district": {"abbreviation": "fim", "display_name": "Michigan", "key": "2016fim", "year": 2016}, "division_keys": [], "end_date": "2016-04-02", "event_code": "mihow", "event_type": 1, "event_type_string": "District", "first_event_id": "17413", "gmaps_place_id": "ChIJN2g4qPRHI4gReOm1Nd0HQYI", "gmaps_url": "https://maps.google.com/?cid=9385791745087105400", "key": "2016mihow", "lat": 42.565648, "lng": -83.9274081, "location_name": "Parker Middle School", "name": "FIM District - Howell Event", "parent_event_key": null, "playoff_type": null, "playoff_type_string": null, "postal_code": "48843", "short_name": "Howell", "start_date": "2016-03-31", "state_prov": "MI", "timezone": "America/New_York", "webcasts": [{"channel": "1pmLj4287Ss", "type": "youtube"}, {"channel": "<iframe src=\"http://iframe.dacast.com/b/66716/c/219330\" width=\"100%\" height=\"100%\" frameborder=\"0\" scrolling=\"no\" allowfullscreen webkitallowfullscreen mozallowfullscreen oallowfullscreen msallowfullscreen></iframe>", "type": "iframe"}], "website": "http://www.firstinmichigan.org", "week": 5, "year": 2016}, {"address": "1700 University Ave, Flint, MI 48504, USA", "city": "Flint", "country": "USA", "district": {"abbreviation": "fim", "display_name": "Michigan", "key": "2016fim", "year": 2016}, "division_keys": [], "end_date": "2016-03-12", "event_code": "mike2", "event_type": 1, "event_type_string": "District", "first_event_id": "20823", "gmaps_place_id": "ChIJLx7Nx2SCI4gRzW8R94I3pEw", "gmaps_url": "https://maps.google.com/?cid=5522600078693461965", "key": "2016mike2", "lat": 43.0114011, "lng": -83.712981, "location_name": "Kettering University", "name": "FIM District - Kettering University Event #2", "parent_event_key": null, "playoff_type": null, "playoff_type_string": null, "postal_code": "48504", "short_name": "Kettering University", "start_date": "2016-03-10", "state_prov": "MI", "timezone": "America/New_York", "webcasts": [{"channel": "firstinmichigan2", "type": "twitch"}], "website": "http://www.firstinmichigan.org", "week": 2, "year": 2016}, {"address": "901 N Broadway, St. Louis, MO 63101, USA", "city": "St. Louis", "country": "USA", "district": null, "division_keys": [], "end_date": "2017-04-29", "event_code": "cur", "event_type": 3, "event_type_string": "Championship Division", "first_event_id": null, "gmaps_place_id": "ChIJwcWeSx-z2IcR7shA7mBLmOA", "gmaps_url": "https://maps.google.com/?cid=16183768140642044142", "key": "2017cur", "lat": 38.6328287, "lng": -90.1885095, "location_name": "The Dome at America's Center", "name": "Curie Division", "parent_event_key": "2017cmpmo", "playoff_type": 0, "playoff_type_string": "Elimination Bracket (8 Alliances)", "postal_code": "63101", "short_name": "Curie", "start_date": "2017-04-26", "state_prov": "MO", "timezone": "America/Chicago", "webcasts": [{"channel": "FIRSTInspires_Curie", "type": "twitch"}], "website": null, "week": null, "year": 2017}, {"address": "48710, 7400 Bay Rd, Saginaw, MI 48604, USA", "city": "Saginaw", "country": "USA", "district": {"abbreviation": "fim", "display_name": "Michigan", "key": "2017fim", "year": 2017}, "division_keys": [], "end_date": "2017-04-15", "event_code": "micmp2", "event_type": 5, "event_type_string": "District Championship Division", "first_event_id": null, "gmaps_place_id": "ChIJP-WmCAbdI4gRDHBqkqY4ycc", "gmaps_url": "https://maps.google.com/?cid=14396099971938676748", "key": "2017micmp2", "lat": 43.51391539999999, "lng": -83.9626849, "location_name": "Saginaw Valley State University", "name": "Michigan State Championship - Dow Division", "parent_event_key": "2017micmp", "playoff_type": 0, "playoff_type_string": "Elimination Bracket (8 Alliances)", "postal_code": "48604", "short_name": "MSC - Dow", "start_date": "2017-04-12", "state_prov": "MI", "timezone": "America/New_York", "webcasts": [{"channel": "66716", "file": "219332", "type": "dacast"}], "website": "http://www.firstinmichigan.org", "week": 6, "year": 2017}, {"address": "48710, 7400 Bay Rd, Saginaw, MI 48604, USA", "city": "Saginaw", "country": "USA", "district": {"abbreviation": "fim", "display_name": "Michigan", "key": "2017fim", "year": 2017}, "division_keys": ["2017micmp1", "2017micmp2", "2017micmp3", "2017micmp4"], "end_date": "2017-04-15", "event_code": "micmp", "event_type": 2, "event_type_string": "District Championship", "first_event_id": "22485", "gmaps_place_id": "ChIJP-WmCAbdI4gRDHBqkqY4ycc", "gmaps_url": "https://maps.google.com/?cid=14396099971938676748", "key": "2017micmp", "lat": 43.51391539999999, "lng": -83.9626849, "location_name": "Saginaw Valley State University", "name": "Michigan State Championship", "parent_event_key": null, "playoff_type": 2, "playoff_type_string": "Elimination Bracket (4 Alliances)", "postal_code": "48604", "short_name": "Michigan", "start_date": "2017-04-15", "state_prov": "MI", "timezone": "America/New_York", "webcasts": [{"channel": "https://wowzaprodhd16-lh.akamaihd.net/i/8bf06b90_1@412970/master.m3u8", "type": "html5"}], "website": "http://www.firstinmichigan.org", "week": 6, "year": 2017}, {"address": "1700 University Ave, Flint, MI 48504, USA", "city": "Flint", "country": "USA", "district": {"abbreviation": "fim", "display_name": "Michigan", "key": "2017fim", "year": 2017}, "division_keys": [], "end_date": "2017-03-11", "event_code": "mike2", "event_type": 1, "event_type_string": "District", "first_event_id": "22711", "gmaps_place_id": "ChIJLx7Nx2SCI4gRzW8R94I3pEw", "gmaps_url": "https://maps.google.com/?cid=5522600078693461965", "key": "2017mike2", "lat": 43.0114011, "lng": -83.712981, "location_name": "Kettering University", "name": "FIM District - Kettering University Event #2", "parent_event_key": null, "playoff_type": null, "playoff_type_string": null, "postal_code": "48504", "short_name": "Kettering University #2", "start_date": "2017-03-09", "state_prov": "MI", "timezone": "America/New_York", "webcasts": [{"channel": "66716", "file": "219328", "type": "dacast"}], "website": "http://www.firstinmichigan.org", "week": 1, "year": 2017}, {"address": "1001 S Barnes St, Mason, MI 48854, USA", "city": "Mason", "country": "USA", "district": {"abbreviation": "fim", "display_name": "Michigan", "key": "2017fim", "year": 2017}, "division_keys": [], "end_date": "2017-03-25", "event_code": "milan", "event_type": 1, "event_type_string": "District", "first_event_id": "22659", "gmaps_place_id": "ChIJHf0B-gDQIogRWDx3YpO4CCA", "gmaps_url": "https://maps.google.com/?cid=2308297752179063896", "key": "2017milan", "lat": 42.570886, "lng": -84.4353129, "location_name": "Mason High School", "name": "FIM District - Lansing Event", "parent_event_key": null, "playoff_type": null, "playoff_type_string": null, "postal_code": "48854", "short_name": "Lansing", "start_date": "2017-03-23", "state_prov": "MI", "timezone": "America/New_York", "webcasts": [{"channel": "66716", "file": "219328", "type": "dacast"}], "website": "http://www.firstinmichigan.org", "week": 3, "year": 2017}], "districs": [{"abbreviation": "fim", "display_name": "Michigan", "key": "2009fim", "year": 2009}, {"abbreviation": "fim", "display_name": "Michigan", "key": "2010fim", "year": 2010}, {"abbreviation": "fim", "display_name": "Michigan", "key": "2011fim", "year": 2011}, {"abbreviation": "fim", "display_name": "Michigan", "key": "2012fim", "year": 2012}, {"abbreviation": "fim", "display_name": "Michigan", "key": "2013fim", "year": 2013}, {"abbreviation": "fim", "display_name": "Michigan", "key": "2014fim", "year": 2014}, {"abbreviation": "fim", "display_name": "Michigan", "key": "2015fim", "year": 2015}, {"abbreviation": "fim", "display_name": "Michigan", "key": "2016fim", "year": 2016}, {"abbreviation": "fim", "display_name": "Michigan", "key": "2017fim", "year": 2017}], "awards": [{"award_type": 19, "event_key": "2003cmp", "name": "Sportsmanship-GP", "recipient_list": [{"awardee": null, "team_key": "frc494"}], "year": 2003}, {"award_type": 2, "event_key": "2003cmp", "name": "Championship Finalist", "recipient_list": [{"awardee": null, "team_key": "frc25"}, {"awardee": null, "team_key": "frc343"}, {"awardee": null, "team_key": "frc494"}], "year": 2003}, {"award_type": 1, "event_key": "2003cur", "name": "Division Champion", "recipient_list": [{"awardee": null, "team_key": "frc25"}, {"awardee": null, "team_key": "frc343"}, {"awardee": null, "team_key": "frc494"}], "year": 2003}, {"award_type": 1, "event_key": "2003ga", "name": "Regional Winner", "recipient_list": [{"awardee": null, "team_key": "frc34"}, {"awardee": null, "team_key": "frc494"}, {"awardee": null, "team_key": "frc1180"}], "year": 2003}, {"award_type": 9, "event_key": "2003ga", "name": "Engineering Inspiration Award", "recipient_list": [{"awardee": null, "team_key": "frc494"}], "year": 2003}, {"award_type": 13, "event_key": "2003gl", "name": "Judges Award Friday", "recipient_list": [{"awardee": null, "team_key": "frc830"}, {"awardee": null, "team_key": "frc494"}, {"awardee": null, "team_key": "frc292"}], "year": 2003}, {"award_type": 17, "event_key": "2003oh", "name": "Motorola Quality Award", "recipient_list": [{"awardee": null, "team_key": "frc494"}], "year": 2003}, {"award_type": 1, "event_key": "2004arc", "name": "Division Champion", "recipient_list": [{"awardee": null, "team_key": "frc71"}, {"awardee": null, "team_key": "frc435"}, {"awardee": null, "team_key": "frc494"}], "year": 2004}, {"award_type": 1, "event_key": "2004cmp", "name": "Championship Winner", "recipient_list": [{"awardee": null, "team_key": "frc71"}, {"awardee": null, "team_key": "frc435"}, {"awardee": null, "team_key": "frc494"}], "year": 2004}, {"award_type": 17, "event_key": "2004cmp", "name": "Quality", "recipient_list": [{"awardee": null, "team_key": "frc494"}], "year": 2004}, {"award_type": 19, "event_key": "2004cmp", "name": "Sportsmanship-GP", "recipient_list": [{"awardee": null, "team_key": "frc494"}], "year": 2004}, {"award_type": 17, "event_key": "2004ga", "name": "Motorola Quality Award", "recipient_list": [{"awardee": null, "team_key": "frc494"}], "year": 2004}, {"award_type": 3, "event_key": "2004ga", "name": "Regional Woodie Flowers Award", "recipient_list": [{"awardee": "Jay Tenbrick", "team_key": "frc494"}], "year": 2004}, {"award_type": 2, "event_key": "2004gl", "name": "Regional Finalist", "recipient_list": [{"awardee": null, "team_key": "frc280"}, {"awardee": null, "team_key": "frc494"}, {"awardee": null, "team_key": "frc503"}], "year": 2004}, {"award_type": 19, "event_key": "2004mi", "name": "Johnson & Johnson Sportsmanship Award", "recipient_list": [{"awardee": null, "team_key": "frc494"}], "year": 2004}, {"award_type": 2, "event_key": "2004mi", "name": "Regional Finalist", "recipient_list": [{"awardee": null, "team_key": "frc494"}, {"awardee": null, "team_key": "frc67"}, {"awardee": null, "team_key": "frc858"}], "year": 2004}, {"award_type": 27, "event_key": "2004mi", "name": "Imagery Award", "recipient_list": [{"awardee": null, "team_key": "frc494"}], "year": 2004}, {"award_type": 2, "event_key": "2005arc", "name": "Division Finalist", "recipient_list": [{"awardee": null, "team_key": "frc179"}, {"awardee": null, "team_key": "frc191"}, {"awardee": null, "team_key": "frc494"}], "year": 2005}, {"award_type": 38, "event_key": "2005dt", "name": "Leadership in Controls", "recipient_list": [{"awardee": null, "team_key": "frc494"}], "year": 2005}, {"award_type": 17, "event_key": "2005mi", "name": "Motorola Quality", "recipient_list": [{"awardee": null, "team_key": "frc494"}], "year": 2005}, {"award_type": 18, "event_key": "2005mi", "name": "Safety", "recipient_list": [{"awardee": null, "team_key": "frc494"}], "year": 2005}, {"award_type": 1, "event_key": "2005roc", "name": "Regional Winner", "recipient_list": [{"awardee": null, "team_key": "frc191"}, {"awardee": null, "team_key": "frc494"}, {"awardee": null, "team_key": "frc639"}], "year": 2005}, {"award_type": 18, "event_key": "2005roc", "name": "Safety Award", "recipient_list": [{"awardee": null, "team_key": "frc494"}], "year": 2005}, {"award_type": 16, "event_key": "2006cmp", "name": "Industrial Design", "recipient_list": [{"awardee": null, "team_key": "frc494"}], "year": 2006}, {"award_type": 18, "event_key": "2006mi", "name": "Underwriters Laboratories Industrial Safety Award", "recipient_list": [{"awardee": null, "team_key": "frc494"}], "year": 2006}, {"award_type": 20, "event_key": "2006mi", "name": "Xerox Creativity Award", "recipient_list": [{"awardee": null, "team_key": "frc494"}], "year": 2006}, {"award_type": 1, "event_key": "2006oh", "name": "Regional Winner", "recipient_list": [{"awardee": null, "team_key": "frc272"}, {"awardee": null, "team_key": "frc494"}, {"awardee": null, "team_key": "frc174"}], "year": 2006}, {"award_type": 29, "event_key": "2006oh", "name": "Radio Shack Innovation in Control Award", "recipient_list": [{"awardee": null, "team_key": "frc494"}], "year": 2006}, {"award_type": 17, "event_key": "2006wi", "name": "Motorola Quality Award", "recipient_list": [{"awardee": null, "team_key": "frc494"}], "year": 2006}, {"award_type": 2, "event_key": "2006wi", "name": "Regional Finalist", "recipient_list": [{"awardee": null, "team_key": "frc70"}, {"awardee": null, "team_key": "frc494"}, {"awardee": null, "team_key": "frc1781"}], "year": 2006}, {"award_type": 2, "event_key": "2007gl", "name": "Regional Finalist", "recipient_list": [{"awardee": null, "team_key": "frc494"}, {"awardee": null, "team_key": "frc1023"}, {"awardee": null, "team_key": "frc1503"}], "year": 2007}, {"award_type": 1, "event_key": "2007mi", "name": "Regional Winner", "recipient_list": [{"awardee": null, "team_key": "frc703"}, {"awardee": null, "team_key": "frc469"}, {"awardee": null, "team_key": "frc494"}], "year": 2007}, {"award_type": 32, "event_key": "2007mi", "name": "Autodesk Visualization Award", "recipient_list": [{"awardee": null, "team_key": "frc494"}], "year": 2007}, {"award_type": 32, "event_key": "2008mi", "name": "Autodesk Visualization Award", "recipient_list": [{"awardee": null, "team_key": "frc494"}], "year": 2008}, {"award_type": 29, "event_key": "2010gl", "name": "Innovation in Control Award sponsored by Rockwell Automation", "recipient_list": [{"awardee": null, "team_key": "frc494"}], "year": 2010}, {"award_type": 2, "event_key": "2011gg", "name": "Finalist", "recipient_list": [{"awardee": null, "team_key": "frc1243"}, {"awardee": null, "team_key": "frc494"}, {"awardee": null, "team_key": "frc1684"}], "year": 2011}, {"award_type": 27, "event_key": "2011gg", "name": "Imagery Award in honor of Jack Kamen", "recipient_list": [{"awardee": null, "team_key": "frc494"}], "year": 2011}, {"award_type": 1, "event_key": "2011wc", "name": "Winner", "recipient_list": [{"awardee": null, "team_key": "frc2337"}, {"awardee": null, "team_key": "frc494"}, {"awardee": null, "team_key": "frc66"}], "year": 2011}, {"award_type": 29, "event_key": "2012gg", "name": "Innovation in Control Award sponsored by Rockwell Automation", "recipient_list": [{"awardee": null, "team_key": "frc494"}], "year": 2012}, {"award_type": 13, "event_key": "2012swm", "name": "Judges' Award", "recipient_list": [{"awardee": null, "team_key": "frc494"}], "year": 2012}, {"award_type": 21, "event_key": "2013miwfd", "name": "Excellence in Engineering Award sponsored by Delphi", "recipient_list": [{"awardee": null, "team_key": "frc494"}], "year": 2013}, {"award_type": 2, "event_key": "2014mibed", "name": "Finalist", "recipient_list": [{"awardee": null, "team_key": "frc494"}, {"awardee": null, "team_key": "frc70"}, {"awardee": null, "team_key": "frc3536"}], "year": 2014}, {"award_type": 29, "event_key": "2014mibed", "name": "Innovation in Control Award sponsored by Rockwell Automation", "recipient_list": [{"awardee": null, "team_key": "frc494"}], "year": 2014}, {"award_type": 29, "event_key": "2014micen", "name": "Innovation in Control Award sponsored by Rockwell Automation", "recipient_list": [{"awardee": null, "team_key": "frc494"}], "year": 2014}, {"award_type": 29, "event_key": "2014micmp", "name": "Innovation in Control Award sponsored by Rockwell Automation", "recipient_list": [{"awardee": null, "team_key": "frc494"}], "year": 2014}, {"award_type": 1, "event_key": "2014miwmi", "name": "Winner", "recipient_list": [{"awardee": null, "team_key": "frc494"}, {"awardee": null, "team_key": "frc2054"}, {"awardee": null, "team_key": "frc4956"}], "year": 2014}, {"award_type": 16, "event_key": "2014miwmi", "name": "Industrial Design Award sponsored by General Motors", "recipient_list": [{"awardee": null, "team_key": "frc494"}], "year": 2014}, {"award_type": 17, "event_key": "2015mihow", "name": "Quality Award sponsored by Motorola", "recipient_list": [{"awardee": null, "team_key": "frc494"}], "year": 2015}, {"award_type": 2, "event_key": "2015misjo", "name": "District Event Finalist", "recipient_list": [{"awardee": null, "team_key": "frc70"}, {"awardee": null, "team_key": "frc494"}, {"awardee": null, "team_key": "frc5623"}], "year": 2015}, {"award_type": 20, "event_key": "2015misjo", "name": "Creativity Award sponsored by Xerox", "recipient_list": [{"awardee": null, "team_key": "frc494"}], "year": 2015}, {"award_type": 2, "event_key": "2016gal", "name": "Championship Subdivision Finalist", "recipient_list": [{"awardee": null, "team_key": "frc558"}, {"awardee": null, "team_key": "frc494"}, {"awardee": null, "team_key": "frc2502"}, {"awardee": null, "team_key": "frc4740"}], "year": 2016}, {"award_type": 2, "event_key": "2016mike2", "name": "District Event Finalist", "recipient_list": [{"awardee": null, "team_key": "frc494"}, {"awardee": null, "team_key": "frc3534"}, {"awardee": null, "team_key": "frc6085"}], "year": 2016}, {"award_type": 29, "event_key": "2016mike2", "name": "Innovation in Control Award sponsored by Rockwell Automation", "recipient_list": [{"awardee": null, "team_key": "frc494"}], "year": 2016}, {"award_type": 18, "event_key": "2017micmp2", "name": "Safety Award sponsored by Underwriters Laboratories", "recipient_list": [{"awardee": null, "team_key": "frc494"}], "year": 2017}, {"award_type": 18, "event_key": "2017mike2", "name": "Safety Award sponsored by Underwriters Laboratories", "recipient_list": [{"awardee": null, "team_key": "frc494"}], "year": 2017}, {"award_type": 29, "event_key": "2017mike2", "name": "Innovation in Control Award sponsored by Rockwell Automation", "recipient_list": [{"awardee": null, "team_key": "frc494"}], "year": 2017}, {"award_type": 1, "event_key": "2017milan", "name": "District Event Winner", "recipient_list": [{"awardee": null, "team_key": "frc3357"}, {"awardee": null, "team_key": "frc494"}, {"awardee": null, "team_key": "frc308"}], "year": 2017}, {"award_type": 17, "event_key": "2017milan", "name": "Quality Award sponsored by Motorola Solutions Foundation", "recipient_list": [{"awardee": null, "team_key": "frc494"}], "year": 2017}]}