{"info": {"address": null, "city": "Toronto", "country": "Canada", "gmaps_place_id": null, "gmaps_url": null, "home_championship": {"2017": "St. Louis", "2018": "Detroit"}, "key": "frc5580", "lat": null, "lng": null, "location_name": null, "motto": null, "name": "Cedarbrae Collegiate Institute", "nickname": "BRAEZEN KNIGHTS", "postal_code": "M1H2A2", "rookie_year": 2015, "state_prov": "Ontario", "team_number": 5580, "website": "http://www.firstinspires.org/"}, "events": [{"address": "50 Carlton St, Toronto, ON M5B 1J2, Canada", "city": "Toronto", "country": "Canada", "district": null, "division_keys": [], "end_date": "2015-03-07", "event_code": "onto2", "event_type": 0, "event_type_string": "Regional", "first_event_id": "13411", "gmaps_place_id": "ChIJiZoptbQ0K4gR6b-AhlvIqfI", "gmaps_url": "https://maps.google.com/?cid=17485727323666825193", "key": "2015onto2", "lat": 43.6620418, "lng": -79.38020639999999, "location_name": "Mattamy Athletic Centre", "name": "Greater Toronto Central Regional", "parent_event_key": null, "playoff_type": 3, "playoff_type_string": "Average Score (8 Alliances)", "postal_code": "M5B 1J2", "short_name": "Greater Toronto Central", "start_date": "2015-03-04", "state_prov": "ON", "timezone": "America/Toronto", "webcasts": [{"channel": "12312913", "file": "3839990", "type": "livestream"}], "website": "http://www.firstroboticscanada.org", "week": 1, "year": 2015}, {"address": "2000 Simcoe St N, Oshawa, ON L1H 7K4, Canada", "city": "Oshawa", "country": "Canada", "district": null, "division_keys": [], "end_date": "2016-03-12", "event_code": "onto", "event_type": 0, "event_type_string": "Regional", "first_event_id": "17355", "gmaps_place_id": "ChIJf674apob1YkR9RY3WRk6Nyo", "gmaps_url": "https://maps.google.com/?cid=3041963953857435381", "key": "2016onto", "lat": 43.9453764, "lng": -78.896397, "location_name": "University of Ontario Institute of Technology", "name": "Greater Toronto East Regional ", "parent_event_key": null, "playoff_type": null, "playoff_type_string": null, "postal_code": "L1H 7K4", "short_name": "Greater Toronto East", "start_date": "2016-03-09", "state_prov": "ON", "timezone": "America/Toronto", "webcasts": [{"channel": "12312913", "file": "4953783", "type": "livestream"}], "website": "http://www.firstroboticscanada.org", "week": 2, "year": 2016}], "districs": [], "awards": []}