{"info": {"address": null, "city": "Port Huron", "country": "USA", "gmaps_place_id": null, "gmaps_url": null, "home_championship": {"2017": "St. Louis", "2018": "Detroit"}, "key": "frc6551", "lat": null, "lng": null, "location_name": null, "motto": null, "name": "4-H Youth Development Organization", "nickname": "MOOTeam", "postal_code": "48060", "rookie_year": 2017, "state_prov": "Michigan", "team_number": 6551, "website": "http://scc4hrobotics.com"}, "events": [], "districs": [{"abbreviation": "fim", "display_name": "Michigan", "key": "2017fim", "year": 2017}], "awards": []}